README
setup.py
virtualenvwrapper/__init__.py
virtualenvwrapper/configvars.py
virtualenvwrapper.configvar.egg-info/PKG-INFO
virtualenvwrapper.configvar.egg-info/SOURCES.txt
virtualenvwrapper.configvar.egg-info/dependency_links.txt
virtualenvwrapper.configvar.egg-info/entry_points.txt
virtualenvwrapper.configvar.egg-info/namespace_packages.txt
virtualenvwrapper.configvar.egg-info/requires.txt
virtualenvwrapper.configvar.egg-info/top_level.txt