Metadata-Version: 1.0
Name: virtualenvwrapper.configvar
Version: 0.1
Summary: Plugin for virtualenvwrapper to automatically export config vars found in your project level .env file.
Home-page: https://github.com/seanbrant/virtualenvwrapper.configvar
Author: Sean Brant
Author-email: brant.sean@gmail.com
License: UNKNOWN
Platform: UNKNOWN
